CHANGELOG.txt
LICENCE.txt
MANIFEST.in
README.txt
__init__.py
setup.py
Akram_Hssaini.egg-info/PKG-INFO
Akram_Hssaini.egg-info/SOURCES.txt
Akram_Hssaini.egg-info/dependency_links.txt
Akram_Hssaini.egg-info/requires.txt
Akram_Hssaini.egg-info/top_level.txt
file/loader.py